<?xml version="1.0" encoding="utf-8" ?>
<dwsync>
    <file name="on_delete.php" server="Z:/" local="129658725279271164" remote="129658725270000000"/>
    <file name="on_save.php" server="Z:/" local="129658725279236160" remote="129658725270000000"/>
    <file name="on_show_form.php" server="Z:/" local="129658725279301168" remote="129658725270000000"/>
    <file name="on_show_form.php" server="Z:/sCMS/" local="129715353641998376" remote="129715353640000000"/>
    <file name="on_save.php" server="Z:/sCMS/" local="129715584107844200" remote="129715584100000000"/>
    <file name="on_show_form.php" server="149.154.152.228//var/www/regija_zapadna/" local="130032559070763288"
          remote="130032561250000000"/>
    <file name="on_delete.php" server="149.154.152.228//var/www/regija_zapadna/" local="130032517091675125"
          remote="130032561260000000"/>
    <file name="on_save.php" server="149.154.152.228//var/www/regija_zapadna/" local="130032561818256910"
          remote="130032561270000000"/>
    <file name="on_show_form.php" server="www.local-info.hr//var/www/local-info.hr/develop_html/"
          local="130032583211962997" remote="130032582080000000"/>
    <file name="on_delete.php" server="www.local-info.hr//var/www/local-info.hr/develop_html/"
          local="130032517091675125" remote="130032569960000000"/>
    <file name="on_save.php" server="www.local-info.hr//var/www/local-info.hr/develop_html/" local="130032561818256910"
          remote="130032569960000000"/>
</dwsync>